mangamon/__init__.py
mangamon/command_line.py
mangamon/constants.py
mangamon/download.py
mangamon/manga.py
mangamon/post_processor.py
mangamon/util.py
mangamon-0.0.3.dist-info/LICENSE
mangamon-0.0.3.dist-info/METADATA
mangamon-0.0.3.dist-info/WHEEL
mangamon-0.0.3.dist-info/entry_points.txt
mangamon-0.0.3.dist-info/top_level.txt
mangamon-0.0.3.dist-info/RECORD
